Workbook

Sheet PREMISSAS
A1: ANÁLISE DE PRICING - FLOWKER
A2: Premissas Editáveis (células amarelas)
A4: TAXA DE CÂMBIO
A5: USD para BRL | B5: 5 | C5: BRL/USD | D5: ← EDITÁVEL: Ajuste conforme câmbio atual
A7: PREÇOS DE CLOUD (USD/mês)
A8: Componente | B8: Preço USD | C8: Preço BRL | D8: Configuração
A9: PostgreSQL (RDS) | B9: 108 | C9: =B9*B5 | D9: db.r6g.large (2 vCPU, 16GB)
A10: MongoDB (Atlas) | B10: 389 | C10: =B10*B5 | D10: M30 (2 vCPU, 8GB)
A11: Valkey (ElastiCache) | B11: 94 | C11: =B11*B5 | D11: cache.r6g.large (2 vCPU, 13GB)
A12: Temporal Cloud | B12: 25 | C12: =B12*B5 | D12: Base plan
A13: RabbitMQ (Amazon MQ) | B13: 180 | C13: =B13*B5 | D13: mq.m5.large (2 vCPU, 8GB)
A14: Compute (EKS) | B14: 122 | C14: =B14*B5 | D14: 2x c6g.large (2 vCPU, 4GB each)
A15: TOTAL INFRA | B15: =SUM(B9:B14) | C15: =B15*B5
A17: OPERAÇÕES POR WORKFLOW
A18: Operação | B18: Quantidade | C18: Unidade | D18: Fonte
A19: Temporal Actions | B19: 9 | C19: actions/wf | D19: Código: validation_workflow.go
A20: MongoDB Operations | B20: 6 | C20: ops/wf | D20: Código: activities.go (audit writes)
A21: Valkey Operations | B21: 12 | C21: ops/wf | D21: Código: locks + cache
A23: CUSTOS POR OPERAÇÃO (USD)
A24: Operação | B24: Custo USD | C24: Unidade | D24: Fonte
A25: Temporal (por action) | B25: 2.5e-05 | C25: USD/action | D25: Temporal Cloud Pricing
A26: MongoDB (por operação) | B26: 1e-06 | C26: USD/op | D26: Estimativa Atlas
A27: Valkey (por operação) | B27: 1e-07 | C27: USD/op | D27: Estimativa ElastiCache
A29: CENÁRIO DE VOLUME
A30: Workflows por mês (cliente típico) | B30: 25000 | D30: ← Volume médio esperado por cliente
A31: % Infra compartilhada (best case) | B31: 0.25 | D31: ← Flowker usa X% do cluster compartilhado
A33: PRICING TIERS
A34: Tier | B34: Base (BRL) | C34: Por WF (BRL) | D34: Limite WF/mês
A35: Starter | B35: 0 | C35: 0 | D35: 1000
A36: Growth | B36: 2990 | C36: 0.08 | D36: 25000
A37: Scale | B37: 9990 | C37: 0.04 | D37: 200000
A38: Enterprise | B38: 19990 | C38: 0.02 | D38: 1000000
A41: REFERÊNCIAS INTERNAS (não editar)
A42: Custo Variável/WF (USD) | B42: =(B19*B25)+(B20*B26)+(B21*B27)
A43: Custo Variável/WF (BRL) | B43: =B42*B5

Sheet CUSTOS
A1: ANÁLISE DE CUSTOS - FLOWKER
A3: CUSTOS FIXOS MENSAIS (Infraestrutura Standalone)
A4: Componente | B4: Custo USD | C4: Custo BRL | D4: % do Total | E4: Confiança
A5: PostgreSQL (RDS) | B5: =PREMISSAS!B9 | C5: =B5*PREMISSAS!B5 | D5: =B5/B11 | E5: 🟢 Alto
A6: MongoDB (Atlas) | B6: =PREMISSAS!B10 | C6: =B6*PREMISSAS!B5 | D6: =B6/B11 | E6: 🟢 Alto
A7: Valkey (ElastiCache) | B7: =PREMISSAS!B11 | C7: =B7*PREMISSAS!B5 | D7: =B7/B11 | E7: 🟢 Alto
A8: Temporal Cloud | B8: =PREMISSAS!B12 | C8: =B8*PREMISSAS!B5 | D8: =B8/B11 | E8: 🟢 Alto
A9: RabbitMQ (Amazon MQ) | B9: =PREMISSAS!B13 | C9: =B9*PREMISSAS!B5 | D9: =B9/B11 | E9: 🟢 Alto
A10: Compute (EKS) | B10: =PREMISSAS!B14 | C10: =B10*PREMISSAS!B5 | D10: =B10/B11 | E10: 🟢 Alto
A11: TOTAL CUSTO FIXO | B11: =SUM(B5:B10) | C11: =B11*PREMISSAS!B5 | D11: =100%
A13: CUSTOS VARIÁVEIS (por Workflow)
A14: Componente | B14: Ops/WF | C14: Custo/Op (USD) | D14: Custo/WF (USD) | E14: Confiança
A15: Temporal Actions | B15: =PREMISSAS!B19 | C15: =PREMISSAS!B26 | D15: =B15*C15 | E15: 🟠 Baixo-Médio
A16: MongoDB Operations | B16: =PREMISSAS!B20 | C16: =PREMISSAS!B27 | D16: =B16*C16 | E16: 🟠 Baixo-Médio
A17: Valkey Operations | B17: =PREMISSAS!B21 | C17: =PREMISSAS!B28 | D17: =B17*C17 | E17: 🟠 Baixo-Médio
A18: TOTAL CUSTO VARIÁVEL/WF (USD) | D18: =SUM(D15:D17)
A19: TOTAL CUSTO VARIÁVEL/WF (BRL) | D19: =D18*PREMISSAS!B5

Sheet BREAK_EVEN
A1: ANÁLISE DE BREAK-EVEN
A2: Fórmula: Break-even = Custo Fixo / (Preço/WF - Custo Variável/WF)
A4: Custo Fixo Mensal (BRL): | B4: =CUSTOS!C11
A5: Custo Variável/WF (BRL): | B5: =CUSTOS!D19
A7: BREAK-EVEN POR PREÇO
A8: Preço/WF (BRL) | B8: Margem/WF (BRL) | C8: Break-even (WF) | D8: Clientes Equiv.* | E8: Viabilidade
A9: 0.05 | B9: =A9-B5 | C9: =IF(B9>0,B4/B9,"N/A") | D9: =IF(ISNUMBER(C9),C9/PREMISSAS!B31,"N/A") | E9: =IF(D9<=1,"✅ Excelente",IF(D9<=2,"✅ Bom",IF(D9<=4,"⚠️ Aceitável","❌ Arriscado")))
A10: 0.08 | B10: =A10-B5 | C10: =IF(B10>0,B4/B10,"N/A") | D10: =IF(ISNUMBER(C10),C10/PREMISSAS!B31,"N/A") | E10: =IF(D10<=1,"✅ Excelente",IF(D10<=2,"✅ Bom",IF(D10<=4,"⚠️ Aceitável","❌ Arriscado")))
A11: 0.1 | B11: =A11-B5 | C11: =IF(B11>0,B4/B11,"N/A") | D11: =IF(ISNUMBER(C11),C11/PREMISSAS!B31,"N/A") | E11: =IF(D11<=1,"✅ Excelente",IF(D11<=2,"✅ Bom",IF(D11<=4,"⚠️ Aceitável","❌ Arriscado")))
A12: 0.15 | B12: =A12-B5 | C12: =IF(B12>0,B4/B12,"N/A") | D12: =IF(ISNUMBER(C12),C12/PREMISSAS!B31,"N/A") | E12: =IF(D12<=1,"✅ Excelente",IF(D12<=2,"✅ Bom",IF(D12<=4,"⚠️ Aceitável","❌ Arriscado")))
A13: 0.2 | B13: =A13-B5 | C13: =IF(B13>0,B4/B13,"N/A") | D13: =IF(ISNUMBER(C13),C13/PREMISSAS!B31,"N/A") | E13: =IF(D13<=1,"✅ Excelente",IF(D13<=2,"✅ Bom",IF(D13<=4,"⚠️ Aceitável","❌ Arriscado")))
A15: *Assumindo cliente médio com volume da aba PREMISSAS

Sheet CENARIOS
A1: CENÁRIOS DE MARGEM
A3: CENÁRIO 1: STANDALONE (Worst Case)
A4: Premissa: 1 cliente, infra 100% dedicada
A6: Workflows/mês: | B6: =PREMISSAS!B31
A7: Tier: | B7: Growth
A8: Receita Base: | B8: =PREMISSAS!B37
A9: Receita Variável: | B9: =B6*PREMISSAS!C37
A10: RECEITA TOTAL: | B10: =B8+B9
A12: Custo Fixo (100% infra): | B12: =CUSTOS!C11
A13: Custo Variável: | B13: =B6*CUSTOS!D19
A14: CUSTO TOTAL: | B14: =B12+B13
A16: MARGEM BRUTA (R$): | B16: =B10-B14
A17: MARGEM BRUTA (%): | B17: =B16/B10
A20: CENÁRIO 2: COMPARTILHADO (Best Case)
A21: Premissa: Múltiplos clientes, infra compartilhada
A23: % da Infra usada: | B23: =PREMISSAS!B32
A24: Workflows/mês: | B24: =PREMISSAS!B31
A25: RECEITA TOTAL: | B25: =B10
A27: Custo Fixo (% compartilhado): | B27: =CUSTOS!C11*B23
A28: Custo Variável: | B28: =B24*CUSTOS!D19
A29: CUSTO TOTAL: | B29: =B27+B28
A31: MARGEM BRUTA (R$): | B31: =B25-B29
A32: MARGEM BRUTA (%): | B32: =B31/B25

Sheet PRICING
A1: MODELO DE PRICING - FLOWKER
A2: Simulação com base nas premissas (ajuste na aba PREMISSAS)
A4: SIMULAÇÃO POR TIER
A5: Tier | B5: Base (BRL) | C5: Por WF | D5: Volume | E5: Receita | F5: Custo* | G5: Margem R$ | H5: Margem %
A6: Starter | B6: =PREMISSAS!B36 | C6: =PREMISSAS!C36 | D6: =PREMISSAS!D36 | E6: =B6+(D6*C6) | F6: =CUSTOS!C11+(D6*CUSTOS!D19) | G6: =E6-F6 | H6: =IF(E6>0,G6/E6,0)
A7: Growth | B7: =PREMISSAS!B37 | C7: =PREMISSAS!C37 | D7: =PREMISSAS!D37 | E7: =B7+(D7*C7) | F7: =CUSTOS!C11+(D7*CUSTOS!D19) | G7: =E7-F7 | H7: =IF(E7>0,G7/E7,0)
A8: Scale | B8: =PREMISSAS!B38 | C8: =PREMISSAS!C38 | D8: =PREMISSAS!D38 | E8: =B8+(D8*C8) | F8: =CUSTOS!C11+(D8*CUSTOS!D19) | G8: =E8-F8 | H8: =IF(E8>0,G8/E8,0)
A9: Enterprise | B9: =PREMISSAS!B39 | C9: =PREMISSAS!C39 | D9: =PREMISSAS!D39 | E9: =B9+(D9*C9) | F9: =CUSTOS!C11+(D9*CUSTOS!D19) | G9: =E9-F9 | H9: =IF(E9>0,G9/E9,0)
A11: *Custo assume infra STANDALONE (worst case)
A14: SIMULADOR CUSTOMIZADO
A15: Insira valores:
A16: Preço Base (BRL): | B16: 2990
A17: Preço/WF (BRL): | B17: 0.08
A18: Volume (WF/mês): | B18: 25000
A20: Resultados:
A21: Receita: | B21: =B16+(B18*B17)
A22: Custo (Standalone): | B22: =CUSTOS!C11+(B18*CUSTOS!D19)
A23: Margem (R$): | B23: =B21-B22
A24: Margem (%): | B24: =IF(B21>0,B23/B21,0)
A25: Status: | B25: =IF(B23>0,"✅ Sustentável","❌ Prejuízo")

Sheet CONFIANCA
A1: GRAUS DE CONFIANÇA
A3: Componente | B3: Confiança | C3: Justificativa
A4: Metodologia (standalone-first) | B4: 🟢 Alto | C4: Princípio de negócio, não técnico
A5: Componentes de infraestrutura | B5: 🟢 Alto | C5: Baseado em docker-compose real
A6: Preços de cloud (unitários) | B6: 🟢 Alto | C6: Pricing público verificável AWS/MongoDB
A7: Sizing de produção | B7: 🟠 Baixo-Médio | C7: Sem Terraform/load tests - estimar conservador
A8: Operações por workflow | B8: 🟠 Baixo-Médio | C8: Baseado em código, não em métricas reais
A9: Custo variável por workflow | B9: 🟠 Baixo-Médio | C9: Depende de validação com benchmark
A10: Modelo de pricing (estrutura) | B10: 🟢 Alto | C10: Padrão de mercado (base + variável)
A11: Modelo de pricing (valores) | B11: 🟡 Médio | C11: Depende de validação de custos
A14: AÇÕES PARA AUMENTAR CONFIANÇA
A15: 1. Executar benchmark script com Docker rodando
A16: 2. Instalar KubeCost no cluster K8s
A17: 3. Load test com 25K-100K workflows
A18: 4. Criar Terraform do Flowker
A19: 5. Coletar 30+ dias de dados de billing
