Workbook

Sheet PREMISSAS
A1: ANÁLISE DE PRICING - FLOWKER
A2: Células AMARELAS = Inputs editáveis | Células VERDES = Calculadas
A4: TAXA DE CÂMBIO
A5: USD para BRL | B5: 5 | C5: BRL/USD | D5: ← Ajuste conforme câmbio atual
A7: CUSTOS DE INFRAESTRUTURA (USD/mês) - STANDALONE
A8: Componente | B8: USD/mês | C8: BRL/mês | D8: Configuração
A9: PostgreSQL (RDS db.r6g.large) | B9: 108 | C9: =B9*B5 | D9: 2 vCPU, 16GB RAM
A10: MongoDB (Atlas M30) | B10: 389 | C10: =B10*B5 | D10: 2 vCPU, 8GB RAM
A11: Valkey (ElastiCache cache.r6g.large) | B11: 94 | C11: =B11*B5 | D11: 2 vCPU, 13GB RAM
A12: Temporal Cloud (base) | B12: 25 | C12: =B12*B5 | D12: Orquestração de workflows
A13: RabbitMQ (Amazon MQ mq.m5.large) | B13: 180 | C13: =B13*B5 | D13: 2 vCPU, 8GB RAM
A14: Compute (EKS 2x c6g.large) | B14: 122 | C14: =B14*B5 | D14: 4 vCPU total, 8GB RAM
A15: TOTAL CUSTO FIXO MENSAL | B15: =SUM(B9:B14) | C15: =B15*B5
A17: OPERAÇÕES POR WORKFLOW (baseado em código)
A18: Operação | B18: Qtd/WF | C18: Unidade | D18: Fonte (arquivo)
A19: Temporal Actions | B19: 9 | C19: actions | D19: validation_workflow.go
A20: MongoDB Operations | B20: 6 | C20: ops | D20: activities.go (audit)
A21: Valkey Operations | B21: 12 | C21: ops | D21: activities.go (locks/cache)
A23: CUSTOS POR OPERAÇÃO (USD)
A24: Operação | B24: USD/op | C24: BRL/op | D24: Fonte
A25: Temporal (por action) | B25: 2.5e-05 | C25: =B25*B5 | D25: Temporal Cloud Pricing
A26: MongoDB (por operação) | B26: 1e-06 | C26: =B26*B5 | D26: Estimativa Atlas
A27: Valkey (por operação) | B27: 1e-07 | C27: =B27*B5 | D27: Estimativa ElastiCache
A29: VOLUME DE WORKFLOWS
A30: Workflows/mês (cliente típico Growth) | B30: 25000 | D30: ← Volume médio esperado por cliente
A32: PRICING TIERS
A33: Tier | B33: Base (BRL) | C33: Por WF (BRL) | D33: Limite WF/mês
A34: Starter | B34: 0 | C34: 0 | D34: 1000
A35: Growth | B35: 2990 | C35: 0.08 | D35: 25000
A36: Scale | B36: 9990 | C36: 0.04 | D36: 200000
A37: Enterprise | B37: 19990 | C37: 0.02 | D37: 1000000
A39: CÁLCULOS DERIVADOS (não editar)
A40: Custo Variável/WF (USD) | B40: =(B19*B25)+(B20*B26)+(B21*B27)
A41: Custo Variável/WF (BRL) | B41: =B40*B5
A43: REFERÊNCIAS RÁPIDAS
A44: Custo Fixo Mensal (BRL): =C15
A45: Custo Variável/WF (BRL): =B41
A46: Volume típico: =B30

Sheet CUSTOS
A1: DETALHAMENTO DE CUSTOS
A3: CUSTOS FIXOS MENSAIS (Infraestrutura Standalone)
A4: Componente | B4: USD/mês | C4: BRL/mês | D4: % Total
A5: PostgreSQL | B5: =PREMISSAS!B9 | C5: =B5*PREMISSAS!B5 | D5: =B5/PREMISSAS!B15
A6: MongoDB | B6: =PREMISSAS!B10 | C6: =B6*PREMISSAS!B5 | D6: =B6/PREMISSAS!B15
A7: Valkey | B7: =PREMISSAS!B11 | C7: =B7*PREMISSAS!B5 | D7: =B7/PREMISSAS!B15
A8: Temporal | B8: =PREMISSAS!B12 | C8: =B8*PREMISSAS!B5 | D8: =B8/PREMISSAS!B15
A9: RabbitMQ | B9: =PREMISSAS!B13 | C9: =B9*PREMISSAS!B5 | D9: =B9/PREMISSAS!B15
A10: Compute | B10: =PREMISSAS!B14 | C10: =B10*PREMISSAS!B5 | D10: =B10/PREMISSAS!B15
A11: TOTAL | B11: =SUM(B5:B10) | C11: =SUM(C5:C10) | D11: =100%
A13: CUSTOS VARIÁVEIS (por Workflow)
A14: Componente | B14: Ops/WF | C14: Custo/Op (USD) | D14: Custo/WF (USD)
A15: Temporal Actions | B15: =PREMISSAS!B19 | C15: =PREMISSAS!B25 | D15: =B15*C15
A16: MongoDB Operations | B16: =PREMISSAS!B20 | C16: =PREMISSAS!B26 | D16: =B16*C16
A17: Valkey Operations | B17: =PREMISSAS!B21 | C17: =PREMISSAS!B27 | D17: =B17*C17
A18: TOTAL CUSTO/WF (USD) | D18: =SUM(D15:D17)
A19: TOTAL CUSTO/WF (BRL) | D19: =D18*PREMISSAS!B5

Sheet BREAK_EVEN
A1: ANÁLISE DE BREAK-EVEN (Standalone)
A2: Fórmula: Break-even = Custo Fixo / (Preço/WF - Custo Variável/WF)
A4: Custo Fixo Mensal (BRL): | B4: =PREMISSAS!C15
A5: Custo Variável/WF (BRL): | B5: =PREMISSAS!B41
A6: Volume típico/cliente: | B6: =PREMISSAS!B30
A8: BREAK-EVEN POR PREÇO
A9: Preço/WF | B9: Margem/WF | C9: Break-even (WF) | D9: Clientes* | E9: Viabilidade
A10: 0.05 | B10: =A10-B5 | C10: =IF(B10>0,B4/B10,"N/A") | D10: =IF(ISNUMBER(C10),C10/B6,"N/A") | E10: =IF(D10<=1,"Excelente",IF(D10<=2,"Bom",IF(D10<=4,"Aceitavel","Arriscado")))
A11: 0.08 | B11: =A11-B5 | C11: =IF(B11>0,B4/B11,"N/A") | D11: =IF(ISNUMBER(C11),C11/B6,"N/A") | E11: =IF(D11<=1,"Excelente",IF(D11<=2,"Bom",IF(D11<=4,"Aceitavel","Arriscado")))
A12: 0.1 | B12: =A12-B5 | C12: =IF(B12>0,B4/B12,"N/A") | D12: =IF(ISNUMBER(C12),C12/B6,"N/A") | E12: =IF(D12<=1,"Excelente",IF(D12<=2,"Bom",IF(D12<=4,"Aceitavel","Arriscado")))
A13: 0.15 | B13: =A13-B5 | C13: =IF(B13>0,B4/B13,"N/A") | D13: =IF(ISNUMBER(C13),C13/B6,"N/A") | E13: =IF(D13<=1,"Excelente",IF(D13<=2,"Bom",IF(D13<=4,"Aceitavel","Arriscado")))
A14: 0.2 | B14: =A14-B5 | C14: =IF(B14>0,B4/B14,"N/A") | D14: =IF(ISNUMBER(C14),C14/B6,"N/A") | E14: =IF(D14<=1,"Excelente",IF(D14<=2,"Bom",IF(D14<=4,"Aceitavel","Arriscado")))
A16: *Clientes = Break-even / Volume típico por cliente

Sheet SIMULADOR
A1: SIMULADOR DE MARGEM (Standalone)
A2: Todos os cálculos assumem infraestrutura 100% dedicada
A4: INPUTS DO SIMULADOR
A5: Preço Base (BRL): | B5: 2990 | D5: ← Ajuste o preço base
A6: Preço por Workflow (BRL): | B6: 0.08 | D6: ← Ajuste o preço por workflow
A7: Volume de Workflows/mês: | B7: 25000 | D7: ← Ajuste o volume esperado
A9: RESULTADOS
A10: Receita Base: | B10: =B5
A11: Receita Variável: | B11: =B7*B6
A12: RECEITA TOTAL: | B12: =B5+B11
A14: Custo Fixo (infra standalone): | B14: =PREMISSAS!C15
A15: Custo Variável: | B15: =B7*PREMISSAS!B41
A16: CUSTO TOTAL: | B16: =B14+B15
A18: MARGEM BRUTA (R$): | B18: =B12-B16
A19: MARGEM BRUTA (%): | B19: =IF(B12>0,B18/B12,0)
A21: STATUS: | B21: =IF(B18>0,"SUSTENTAVEL","PREJUIZO")

Sheet CONFIANCA
A1: GRAUS DE CONFIANÇA
A3: Componente | B3: Confiança | C3: Justificativa
A4: Metodologia standalone-first | B4: ALTO | C4: Princípio de negócio conservador
A5: Componentes de infraestrutura | B5: ALTO | C5: Baseado em docker-compose.yml real
A6: Preços de cloud (unitários) | B6: ALTO | C6: Pricing público AWS/MongoDB/Temporal
A7: Sizing de produção | B7: BAIXO-MEDIO | C7: Sem Terraform - estimar conservador
A8: Operações por workflow | B8: BAIXO-MEDIO | C8: Baseado em código, não em métricas
A9: Custo variável por workflow | B9: BAIXO-MEDIO | C9: Requer validação com benchmark
A10: Modelo de pricing (estrutura) | B10: ALTO | C10: Padrão de mercado (base + variável)
A11: Modelo de pricing (valores) | B11: MEDIO | C11: Depende de validação de custos
A14: AÇÕES PARA AUMENTAR CONFIANÇA:
A15: 1. Executar benchmark script com Docker rodando
A16: 2. Instalar KubeCost no cluster K8s
A17: 3. Rodar load test com 25K-100K workflows
A18: 4. Criar Terraform do Flowker para produção
A19: 5. Coletar 30+ dias de dados de billing real
